pyrudof-0.1.142.dist-info/METADATA
pyrudof-0.1.142.dist-info/WHEEL
pyrudof/__init__.py
pyrudof/pyrudof.abi3.so
pyrudof-0.1.142.dist-info/RECORD
