Metadata-Version: 2.4
Name: pyrudof
Version: 0.1.142
Summary: Python bindings for Rudof
Keywords: rdf,linked-data,semantic-web,shex,shacl
Home-Page: https://rudof-project.github.io/rudof
Author: Jose Emilio Labra Gayo <labra@uniovi.es>, Ángel Iglesias Préstamo <angel.iglesias.prestamo@gmail.com>, Marc-Antoine Arnaud <marc-antoine.arnaud@luminvent.com>
Author-email: Jose Emilio Labra Gayo <labra@uniovi.es>, Ángel Iglesias Préstamo <angel.iglesias.prestamo@gmail.com>, Marc-Antoine Arnaud <marc-antoine.arnaud@luminvent.com>
License: MIT OR Apache-2.0
Project-URL: Source Code, https://github.com/rudof-project/rudof
